fcw/__init__.py
fcw/client_python/__init__.py
fcw/client_python/client_common.py
fcw/client_python/client_python.py
fcw/client_python/client_python_simple.py
fcw/client_python/requirements.txt
fcw/client_ros2/__init__.py
fcw/client_ros2/client_ros2/__init__.py
fcw/client_ros2/client_ros2/client_node.py
fcw/client_ros2/package.xml
fcw/client_ros2/resource/client_ros2
fcw/client_ros2/setup.cfg
fcw/client_ros2/setup.py
fcw/client_ros2/test/__init__.py
fcw/client_ros2/test/test_copyright.py
fcw/client_ros2/test/test_flake8.py
fcw/client_ros2/test/test_pep257.py
fcw/core/__init__.py
fcw/core/collision.py
fcw/core/detection.py
fcw/core/fcw_example.py
fcw/core/geometry.py
fcw/core/rate_timer.py
fcw/core/requirements.txt
fcw/core/sort.py
fcw/core/vizualization.py
fcw/core/yolo_detector.py
fcw/service/__init__.py
fcw/service/collision_worker.py
fcw/service/interface.py
fcw/service/requirements.txt
collision_warning_service-0.4.1.dist-info/entry_points.txt
collision_warning_service-0.4.1.dist-info/METADATA
collision_warning_service-0.4.1.dist-info/WHEEL
collision_warning_service-0.4.1.dist-info/RECORD
