Metadata-Version: 2.1
Name: collision-warning-service
Version: 0.4.1
Summary: Early collision warning Network Application for Transportation use case
Home-page: https://github.com/5G-ERA/CollisionWarningService
Author: Petr Kleparnik
Author-email: pkleparnik@cognitechna.cz
Requires-Python: >=3.8
Classifier: Programming Language :: Python :: 3
Classifier: Programming Language :: Python :: 3.8
Classifier: Programming Language :: Python :: 3.9
Classifier: Programming Language :: Python :: 3.10
Classifier: Programming Language :: Python :: 3.11
Requires-Dist: era-5g-client (>=0.4.1)
Requires-Dist: era-5g-interface (>=0.4.1)
Requires-Dist: filterpy (>=1.4.5)
Requires-Dist: flask (>=2.2.3)
Requires-Dist: gitpython (>=3.1.30)
Requires-Dist: more-itertools (>=9.1.0)
Requires-Dist: opencv-python (>=4.6)
Requires-Dist: pandas (>=2.0.0)
Requires-Dist: psutil (>=5.9.4)
Requires-Dist: python-socketio (>=5.8.0)
Requires-Dist: pyyaml (>=6.0)
Requires-Dist: requests (>=2.28.2)
Requires-Dist: seaborn (>=0.12.2)
Requires-Dist: shapely (>=2.0.1)
Requires-Dist: simple-websocket (>=0.9.0)
Requires-Dist: torch (==2.0.0)
Requires-Dist: torchaudio (>=2.0.1,<3.0.0)
Requires-Dist: torchvision (>=0.15.1,<0.16.0)
Requires-Dist: tqdm (>=4.65.0)
Requires-Dist: ultralytics (>=8.0.136)
Project-URL: Repository, https://github.com/5G-ERA/CollisionWarningService
